adua/__init__.py
adua/facerec.py
adua-1.2.3.dist-info/LICENSE
adua-1.2.3.dist-info/METADATA
adua-1.2.3.dist-info/WHEEL
adua-1.2.3.dist-info/top_level.txt
adua-1.2.3.dist-info/RECORD
