Metadata-Version: 2.1
Name: adua
Version: 1.2.3
Summary: You can use this to create your own assistant
Home-page: UNKNOWN
Author: Abhay Bairagi
Author-email: abhaynarayanbairagi@gmail.com
License: UNKNOWN
Platform: UNKNOWN
Requires-Dist: face-recognition
Requires-Dist: opencv-python
Requires-Dist: pyttsx3
Requires-Dist: wikipedia
Requires-Dist: wolframalpha
Requires-Dist: SpeechRecognition
Requires-Dist: openai
Requires-Dist: numpy
Requires-Dist: dlib
